{
  "peliculas": [
    {
      "nombre": "Laura Rita",
      "director": "dsf",
      "image": "img/amelie.jpg",
      "clasificacion": "accion",
      "id": 2
    },
    {
      "nombre": "Laura Rita",
      "director": "dsf",
      "image": "img/amelie.jpg",
      "clasificacion": "accion",
      "id": 3
    },
    {
      "nombre": "Laura Rita",
      "director": "dsf",
      "image": "img/amelie.jpg",
      "clasificacion": "accion",
      "id": 4
    },
    {
      "nombre": "Laura Rita",
      "director": "dsf",
      "image": "img/amelie.jpg",
      "clasificacion": "accion",
      "id": 6
    }
  ],
  "clasificaciones": [
    {
      "nombre": "Drama",
      "id": 1
    },
    {
      "nombre": "Comedia",
      "id": 2
    },
    {
      "nombre": "Documental",
      "id": 3
    },
    {
      "nombre": "Acción",
      "id": 4
    }
  ]
}